olingo_llm_parser/__init__.py
olingo_llm_parser/parser.py
olingo_llm_parser-0.1.8.dist-info/licenses/LICENSE
olingo_llm_parser-0.1.8.dist-info/METADATA
olingo_llm_parser-0.1.8.dist-info/WHEEL
olingo_llm_parser-0.1.8.dist-info/top_level.txt
olingo_llm_parser-0.1.8.dist-info/RECORD
