Metadata-Version: 2.4
Name: olingo-llm-parser
Version: 0.1.8
Summary: Elegant Jinja2-based chat template parser for AI applications
Author-email: Ollsoft Team <info@ollsoft.ai>
Maintainer-email: Ollsoft Team <info@ollsoft.ai>
License: MIT
Project-URL: Homepage, https://github.com/ollsoft-ai/olingo-llm-parser
Project-URL: Documentation, https://olingo-llm-parser.readthedocs.io
Project-URL: Repository, https://github.com/ollsoft-ai/olingo-llm-parser
Project-URL: Bug Tracker, https://github.com/ollsoft-ai/olingo-llm-parser/issues
Keywords: ai,llm,jinja2,chat,template,parser,openai,anthropic
Classifier: Development Status :: 4 - Beta
Classifier: Intended Audience :: Developers
Classifier: License :: OSI Approved :: MIT License
Classifier: Operating System :: OS Independent
Classifier: Programming Language :: Python :: 3
Classifier: Programming Language :: Python :: 3.8
Classifier: Programming Language :: Python :: 3.9
Classifier: Programming Language :: Python :: 3.10
Classifier: Programming Language :: Python :: 3.11
Classifier: Programming Language :: Python :: 3.12
Classifier: Topic :: Software Development :: Libraries :: Python Modules
Classifier: Topic :: Scientific/Engineering :: Artificial Intelligence
Classifier: Topic :: Text Processing :: Markup
Requires-Python: >=3.8
License-File: LICENSE
Requires-Dist: jinja2>=3.0.0
Provides-Extra: dev
Requires-Dist: pytest>=6.0; extra == "dev"
Requires-Dist: pytest-cov; extra == "dev"
Requires-Dist: black; extra == "dev"
Requires-Dist: isort; extra == "dev"
Requires-Dist: flake8; extra == "dev"
Requires-Dist: mypy; extra == "dev"
Provides-Extra: docs
Requires-Dist: sphinx; extra == "docs"
Requires-Dist: sphinx-rtd-theme; extra == "docs"
Dynamic: license-file
